astrogrism/__init__.py
astrogrism/grism_observation.py
astrogrism/version.py
astrogrism/HST/__init__.py
astrogrism/HST/dispersion_models.py
astrogrism/HST/transform_models.py
astrogrism/config/HST/ACS_G800L_CCD1_specwcs.asdf
astrogrism/config/HST/ACS_G800L_CCD2_specwcs.asdf
astrogrism/config/HST/ACS_WFC_distortion.fits
astrogrism/config/HST/WFC3_G102_specwcs.asdf
astrogrism/config/HST/WFC3_G141_specwcs.asdf
astrogrism/config/HST/WFC3_G280_CCD1_specwcs.asdf
astrogrism/config/HST/WFC3_G280_CCD2_specwcs.asdf
astrogrism/config/HST/WFC3_IR_distortion.fits
astrogrism/config/HST/WFC3_UVIS_distortion.fits
astrogrism/config/HST/WFC3_wavelengthrange.asdf
astrogrism/tests/__init__.py
astrogrism/tests/test_acs_g800l.py
astrogrism/tests/test_image2grism.py
astrogrism/tests/test_image2world.py
astrogrism/tests/test_wfc3_g280.py
astrogrism-1.0.1.dist-info/LICENSE.rst
astrogrism-1.0.1.dist-info/METADATA
astrogrism-1.0.1.dist-info/WHEEL
astrogrism-1.0.1.dist-info/top_level.txt
astrogrism-1.0.1.dist-info/RECORD
