Metadata-Version: 2.1
Name: astrogrism
Version: 1.0.1
Summary: HST & JWST Grism Data Analysis
Home-page: https://github.com/spacetelescope/astrogrism
Author: STScI
Author-email: help@stsci.edu
License: BSD
Keywords: astronomy,astrophysics
Platform: UNKNOWN
Classifier: Intended Audience :: Science/Research
Classifier: License :: OSI Approved :: BSD License
Classifier: Operating System :: OS Independent
Classifier: Programming Language :: Python :: 3
Classifier: Programming Language :: Python :: Implementation :: CPython
Classifier: Topic :: Scientific/Engineering :: Astronomy
Classifier: Topic :: Scientific/Engineering :: Physics
Requires-Python: >=3.7
License-File: LICENSE.rst
Requires-Dist: numpy (>=1.17)
Requires-Dist: astropy (>=4)
Requires-Dist: gwcs
Requires-Dist: asdf
Provides-Extra: docs
Requires-Dist: sphinx-automodapi ; extra == 'docs'
Requires-Dist: stsci-rtd-theme ; extra == 'docs'
Provides-Extra: test
Requires-Dist: pytest-astropy-header ; extra == 'test'
Requires-Dist: pytest-doctestplus ; extra == 'test'
Requires-Dist: grismconf ; extra == 'test'
